{
  "POIs": [
    {
      "fit": [
        0.6407583355903625,
        0.7771129012107849,
        0.9289944767951965
      ],
      "name": "SF_tp3"
    },
    {
      "fit": [
        1.4977388381958008,
        2.0,
        2.0
      ],
      "name": "SF_tp2"
    },
    {
      "fit": [
        0.7462875247001648,
        1.1394579410552979,
        1.673980712890625
      ],
      "name": "SF_tp1"
    }
  ],
  "method": "default",
  "params": [
    {
      "SF_tp1": [
        1.1255522966384888,
        1.1396162509918213,
        1.128976583480835
      ],
      "SF_tp2": [
        2.0,
        2.0,
        2.0
      ],
      "SF_tp3": [
        0.7796350121498108,
        0.7771295309066772,
        0.7754736542701721
      ],
      "fit": [
        -0.7150179743766785,
        0.5188324451446533,
        1.4235292673110962
      ],
      "groups": [],
      "impact_SF_tp1": 0.01406395435333252,
      "impact_SF_tp2": 0.0,
      "impact_SF_tp3": 0.002505481243133545,
      "name": "FSRunc_ewk",
      "prefit": [
        -0.9999999999999999,
        0.0,
        0.9999999999999999
      ],
      "type": "Gaussian"
    },
    {
      "SF_tp1": [
        1.0184324979782104,
        1.1394401788711548,
        1.343595027923584
      ],
      "SF_tp2": [
        2.0,
        2.0,
        2.0
      ],
      "SF_tp3": [
        0.7538018226623535,
        0.77711021900177,
        0.8130872845649719
      ],
      "fit": [
        -1.1634551286697388,
        -0.5676710605621338,
        0.29806196689605713
      ],
      "groups": [],
      "impact_SF_tp1": 0.2041548490524292,
      "impact_SF_tp2": 0.0,
      "impact_SF_tp3": 0.035977065563201904,
      "name": "FSRunc_qcd",
      "prefit": [
        -0.9999999999999999,
        0.0,
        0.9999999999999999
      ],
      "type": "Gaussian"
    },
    {
      "SF_tp1": [
        1.1342124938964844,
        1.1394561529159546,
        1.1258141994476318
      ],
      "SF_tp2": [
        2.0,
        2.0,
        2.0
      ],
      "SF_tp3": [
        0.7763243317604065,
        0.7771127223968506,
        0.7778958082199097
      ],
      "fit": [
        -0.9466612339019775,
        -0.01662481389939785,
        0.9164189696311951
      ],
      "groups": [],
      "impact_SF_tp1": 0.013641953468322754,
      "impact_SF_tp2": 0.0,
      "impact_SF_tp3": 0.0007883906364440918,
      "name": "ISRunc_ewk",
      "prefit": [
        -0.9999999999999999,
        0.0,
        0.9999999999999999
      ],
      "type": "Gaussian"
    },
    {
      "SF_tp1": [
        1.1175111532211304,
        1.1394578218460083,
        1.1615878343582153
      ],
      "SF_tp2": [
        2.0,
        2.0,
        2.0
      ],
      "SF_tp3": [
        0.7632997035980225,
        0.7771129012107849,
        0.793052077293396
      ],
      "fit": [
        -0.9890071153640747,
        -0.05765878036618233,
        0.8306703567504883
      ],
      "groups": [],
      "impact_SF_tp1": 0.02213001251220703,
      "impact_SF_tp2": 0.0,
      "impact_SF_tp3": 0.015939176082611084,
      "name": "ISRunc_qcd",
      "prefit": [
        -0.9999999999999999,
        0.0,
        0.9999999999999999
      ],
      "type": "Gaussian"
    },
    {
      "SF_tp1": [
        1.1111466884613037,
        1.139452576637268,
        1.1277354955673218
      ],
      "SF_tp2": [
        2.0,
        2.0,
        2.0
      ],
      "SF_tp3": [
        0.7847313284873962,
        0.7771121263504028,
        0.7783398628234863
      ],
      "fit": [
        -0.7701305150985718,
        0.1686507761478424,
        1.0925049781799316
      ],
      "groups": [],
      "impact_SF_tp1": 0.028305888175964355,
      "impact_SF_tp2": 0.0,
      "impact_SF_tp3": 0.007619202136993408,
      "name": "JER",
      "prefit": [
        -0.9999999999999999,
        0.0,
        0.9999999999999999
      ],
      "type": "Gaussian"
    },
    {
      "SF_tp1": [
        1.081421136856079,
        1.1394388675689697,
        1.0948647260665894
      ],
      "SF_tp2": [
        2.0,
        2.0,
        2.0
      ],
      "SF_tp3": [
        0.7872344851493835,
        0.7771124243736267,
        0.7845331430435181
      ],
      "fit": [
        -0.7175949811935425,
        -0.08461350202560425,
        0.8186529278755188
      ],
      "groups": [],
      "impact_SF_tp1": 0.058017730712890625,
      "impact_SF_tp2": 0.0,
      "impact_SF_tp3": 0.010122060775756836,
      "name": "JES",
      "prefit": [
        -0.9999999999999999,
        0.0,
        0.9999999999999999
      ],
      "type": "Gaussian"
    },
    {
      "SF_tp1": [
        1.1307235956192017,
        1.1394572257995605,
        1.1298753023147583
      ],
      "SF_tp2": [
        2.0,
        2.0,
        2.0
      ],
      "SF_tp3": [
        0.7770583033561707,
        0.7771115899085999,
        0.7768401503562927
      ],
      "fit": [
        -0.9647435545921326,
        -0.028810063377022743,
        0.906737208366394
      ],
      "groups": [],
      "impact_SF_tp1": 0.009581923484802246,
      "impact_SF_tp2": 0.0,
      "impact_SF_tp3": 0.0002714395523071289,
      "name": "L1PreFiringWeight",
      "prefit": [
        -0.9999999999999999,
        0.0,
        0.9999999999999999
      ],
      "type": "Gaussian"
    },
    {
      "SF_tp1": [
        1.128631830215454,
        1.1394541263580322,
        1.1309376955032349
      ],
      "SF_tp2": [
        2.0,
        2.0,
        2.0
      ],
      "SF_tp3": [
        0.7767878770828247,
        0.7771124243736267,
        0.776936411857605
      ],
      "fit": [
        -0.9465420842170715,
        -0.009471396915614605,
        0.9272176027297974
      ],
      "groups": [],
      "impact_SF_tp1": 0.010822296142578125,
      "impact_SF_tp2": 0.0,
      "impact_SF_tp3": 0.00032454729080200195,
      "name": "MuoTrigSF_highPt",
      "prefit": [
        -0.9999999999999999,
        0.0,
        0.9999999999999999
      ],
      "type": "Gaussian"
    },
    {
      "SF_tp1": [
        1.129766821861267,
        1.139461874961853,
        1.129787802696228
      ],
      "SF_tp2": [
        2.0,
        2.0,
        2.0
      ],
      "SF_tp3": [
        0.7768635749816895,
        0.7771133184432983,
        0.7768567204475403
      ],
      "fit": [
        -0.9353983998298645,
        0.0009976086439564824,
        0.9380427002906799
      ],
      "groups": [],
      "impact_SF_tp1": 0.009695053100585938,
      "impact_SF_tp2": 0.0,
      "impact_SF_tp3": 0.00025659799575805664,
      "name": "MuoTrigSF_lowPt",
      "prefit": [
        -0.9999999999999999,
        0.0,
        0.9999999999999999
      ],
      "type": "Gaussian"
    },
    {
      "SF_tp1": [
        1.1299875974655151,
        1.1394554376602173,
        1.1297826766967773
      ],
      "SF_tp2": [
        2.0,
        2.0,
        2.0
      ],
      "SF_tp3": [
        0.7771280407905579,
        0.7771126627922058,
        0.7768614292144775
      ],
      "fit": [
        -0.9336920380592346,
        0.0013237247476354241,
        0.9367727041244507
      ],
      "groups": [],
      "impact_SF_tp1": 0.009672760963439941,
      "impact_SF_tp2": 0.0,
      "impact_SF_tp3": 0.0002512335777282715,
      "name": "MuonIDWeight_uncert_stat",
      "prefit": [
        -0.9999999999999999,
        0.0,
        0.9999999999999999
      ],
      "type": "Gaussian"
    },
    {
      "SF_tp1": [
        1.1298288106918335,
        1.1394574642181396,
        1.1298058032989502
      ],
      "SF_tp2": [
        2.0,
        2.0,
        2.0
      ],
      "SF_tp3": [
        0.776868462562561,
        0.7771128416061401,
        0.7768650650978088
      ],
      "fit": [
        -0.9360220432281494,
        0.0001947243872564286,
        0.9365725517272949
      ],
      "groups": [],
      "impact_SF_tp1": 0.009651660919189453,
      "impact_SF_tp2": 0.0,
      "impact_SF_tp3": 0.00024777650833129883,
      "name": "MuonIDWeight_uncert_syst",
      "prefit": [
        -0.9999999999999999,
        0.0,
        0.9999999999999999
      ],
      "type": "Gaussian"
    },
    {
      "SF_tp1": [
        1.1307259798049927,
        1.1394565105438232,
        1.1297879219055176
      ],
      "SF_tp2": [
        2.0,
        2.0,
        2.0
      ],
      "SF_tp3": [
        0.7770861983299255,
        0.7771127223968506,
        0.7768638134002686
      ],
      "fit": [
        -0.9323173761367798,
        0.0018208854598924518,
        0.9366135597229004
      ],
      "groups": [],
      "impact_SF_tp1": 0.009668588638305664,
      "impact_SF_tp2": 0.0,
      "impact_SF_tp3": 0.00024890899658203125,
      "name": "MuonRecoWeight_uncert_stat",
      "prefit": [
        -0.9999999999999999,
        0.0,
        0.9999999999999999
      ],
      "type": "Gaussian"
    },
    {
      "SF_tp1": [
        1.1298152208328247,
        1.1394578218460083,
        1.1297948360443115
      ],
      "SF_tp2": [
        2.0,
        2.0,
        2.0
      ],
      "SF_tp3": [
        0.7768722176551819,
        0.7771129012107849,
        0.7768639922142029
      ],
      "fit": [
        -0.9352920055389404,
        0.00026914861518889666,
        0.9366047382354736
      ],
      "groups": [],
      "impact_SF_tp1": 0.009662985801696777,
      "impact_SF_tp2": 0.0,
      "impact_SF_tp3": 0.00024890899658203125,
      "name": "MuonRecoWeight_uncert_syst",
      "prefit": [
        -0.9999999999999999,
        0.0,
        0.9999999999999999
      ],
      "type": "Gaussian"
    },
    {
      "SF_tp1": [
        1.1175788640975952,
        1.1394561529159546,
        1.1413832902908325
      ],
      "SF_tp2": [
        2.0,
        2.0,
        2.0
      ],
      "SF_tp3": [
        0.7780568599700928,
        0.777112603187561,
        0.7777747511863708
      ],
      "fit": [
        -0.8459311127662659,
        0.005102748516947031,
        0.9123139977455139
      ],
      "groups": [],
      "impact_SF_tp1": 0.021877288818359375,
      "impact_SF_tp2": 0.0,
      "impact_SF_tp3": 0.0009442567825317383,
      "name": "Pdfweight",
      "prefit": [
        -0.9999999999999999,
        0.0,
        0.9999999999999999
      ],
      "type": "Gaussian"
    },
    {
      "SF_tp1": [
        1.1694670915603638,
        1.139452338218689,
        1.0980584621429443
      ],
      "SF_tp2": [
        2.0,
        2.0,
        2.0
      ],
      "SF_tp3": [
        0.7818185687065125,
        0.7771122455596924,
        0.7724884152412415
      ],
      "fit": [
        -0.6742757558822632,
        0.2230646312236786,
        1.1532325744628906
      ],
      "groups": [],
      "impact_SF_tp1": 0.04139387607574463,
      "impact_SF_tp2": 0.0,
      "impact_SF_tp3": 0.004706323146820068,
      "name": "Pileup",
      "prefit": [
        -0.9999999999999999,
        0.0,
        0.9999999999999999
      ],
      "type": "Gaussian"
    },
    {
      "SF_tp1": [
        1.1357028484344482,
        1.1396033763885498,
        1.1366370916366577
      ],
      "SF_tp2": [
        2.0,
        2.0,
        2.0
      ],
      "SF_tp3": [
        0.7741329669952393,
        0.7771279811859131,
        0.7835008502006531
      ],
      "fit": [
        -1.4035923480987549,
        -0.529740035533905,
        0.30088797211647034
      ],
      "groups": [],
      "impact_SF_tp1": 0.0039005279541015625,
      "impact_SF_tp2": 0.0,
      "impact_SF_tp3": 0.00637286901473999,
      "name": "QCDscale_uncert_ewk",
      "prefit": [
        -0.9999999999999999,
        0.0,
        0.9999999999999999
      ],
      "type": "Gaussian"
    },
    {
      "SF_tp1": [
        1.1137700080871582,
        1.1394493579864502,
        1.193951964378357
      ],
      "SF_tp2": [
        2.0,
        2.0,
        1.9999948740005493
      ],
      "SF_tp3": [
        0.7735958695411682,
        0.7771113514900208,
        0.78729248046875
      ],
      "fit": [
        -0.13387057185173035,
        0.44248154759407043,
        1.2417197227478027
      ],
      "groups": [],
      "impact_SF_tp1": 0.05450260639190674,
      "impact_SF_tp2": 5.125999450683594e-06,
      "impact_SF_tp3": 0.010181128978729248,
      "name": "QCDscale_uncert_qcd",
      "prefit": [
        -0.9999999999999999,
        0.0,
        0.9999999999999999
      ],
      "type": "Gaussian"
    },
    {
      "SF_tp1": [
        1.1371885538101196,
        1.1394578218460083,
        1.1418699026107788
      ],
      "SF_tp2": [
        2.0,
        2.0,
        2.0
      ],
      "SF_tp3": [
        0.7777358889579773,
        0.7771129012107849,
        0.7765587568283081
      ],
      "fit": [
        -0.9262959361076355,
        0.06607627868652344,
        1.0588805675506592
      ],
      "groups": [],
      "impact_SF_tp1": 0.002412080764770508,
      "impact_SF_tp2": 0.0,
      "impact_SF_tp3": 0.0006229877471923828,
      "name": "TptReweight",
      "prefit": [
        -0.9999999999999999,
        0.0,
        0.9999999999999999
      ],
      "type": "Gaussian"
    },
    {
      "SF_tp1": [
        1.1254359483718872,
        1.1394704580307007,
        1.1377290487289429
      ],
      "SF_tp2": [
        2.0,
        2.0,
        2.0
      ],
      "SF_tp3": [
        0.779107391834259,
        0.777113676071167,
        0.7788183093070984
      ],
      "fit": [
        -1.0180577039718628,
        -0.04052228853106499,
        0.9559178948402405
      ],
      "groups": [],
      "impact_SF_tp1": 0.014034509658813477,
      "impact_SF_tp2": 0.0,
      "impact_SF_tp3": 0.001993715763092041,
      "name": "UE",
      "prefit": [
        -0.9999999999999999,
        0.0,
        0.9999999999999999
      ],
      "type": "Gaussian"
    },
    {
      "SF_tp1": [
        1.1383204460144043,
        1.1394578218460083,
        1.14093816280365
      ],
      "SF_tp2": [
        2.0,
        2.0,
        2.0
      ],
      "SF_tp3": [
        0.7766972184181213,
        0.7771129012107849,
        0.7775753736495972
      ],
      "fit": [
        -0.9763389229774475,
        0.018375687301158905,
        1.0126893520355225
      ],
      "groups": [],
      "impact_SF_tp1": 0.0014803409576416016,
      "impact_SF_tp2": 0.0,
      "impact_SF_tp3": 0.00046247243881225586,
      "name": "lumi",
      "prefit": [
        -0.9999999999999999,
        0.0,
        0.9999999999999999
      ],
      "type": "Gaussian"
    },
    {
      "SF_tp1": [
        1.2317274808883667,
        1.1394579410552979,
        1.075003743171692
      ],
      "SF_tp2": [
        2.0,
        2.0,
        2.0
      ],
      "SF_tp3": [
        0.7940271496772766,
        0.7771129012107849,
        0.7671145796775818
      ],
      "fit": [
        0.6669952273368835,
        0.8386790752410889,
        1.0004616975784302
      ],
      "groups": [],
      "impact_SF_tp1": 0.09226953983306885,
      "impact_SF_tp2": 0.0,
      "impact_SF_tp3": 0.0169142484664917,
      "name": "norm_top",
      "prefit": [
        1.0,
        1.0,
        1.0
      ],
      "type": "Unconstrained"
    },
    {
      "SF_tp1": [
        1.1221505403518677,
        1.139474630355835,
        1.094502329826355
      ],
      "SF_tp2": [
        2.0,
        2.0,
        2.0
      ],
      "SF_tp3": [
        0.7710497975349426,
        0.7771151661872864,
        0.7687054872512817
      ],
      "fit": [
        -0.4110512435436249,
        0.24892139434814453,
        0.9051668047904968
      ],
      "groups": [],
      "impact_SF_tp1": 0.04497230052947998,
      "impact_SF_tp2": 0.0,
      "impact_SF_tp3": 0.008409678936004639,
      "name": "otherJMR",
      "prefit": [
        -0.9999999999999999,
        0.0,
        0.9999999999999999
      ],
      "type": "Gaussian"
    },
    {
      "SF_tp1": [
        1.1139001846313477,
        1.139604926109314,
        1.1131401062011719
      ],
      "SF_tp2": [
        2.0,
        2.0,
        2.0
      ],
      "SF_tp3": [
        0.7695695161819458,
        0.7771281003952026,
        0.7706454396247864
      ],
      "fit": [
        -0.4485528767108917,
        0.19499599933624268,
        0.9298853874206543
      ],
      "groups": [],
      "impact_SF_tp1": 0.02646481990814209,
      "impact_SF_tp2": 0.0,
      "impact_SF_tp3": 0.007558584213256836,
      "name": "otherJMS",
      "prefit": [
        -0.9999999999999999,
        0.0,
        0.9999999999999999
      ],
      "type": "Gaussian"
    },
    {
      "SF_tp1": [
        1.1099116802215576,
        1.1394580602645874,
        1.175976276397705
      ],
      "SF_tp2": [
        2.0,
        2.0,
        1.9999990463256836
      ],
      "SF_tp3": [
        0.7734125256538391,
        0.7771129012107849,
        0.7832853198051453
      ],
      "fit": [
        -1.10015070438385,
        -0.2698366343975067,
        0.4653575122356415
      ],
      "groups": [],
      "impact_SF_tp1": 0.036518216133117676,
      "impact_SF_tp2": 9.5367431640625e-07,
      "impact_SF_tp3": 0.0061724185943603516,
      "name": "other_xsec",
      "prefit": [
        -0.9999999999999999,
        0.0,
        0.9999999999999999
      ],
      "type": "Gaussian"
    },
    {
      "SF_tp1": [
        1.0850931406021118,
        1.1396350860595703,
        1.206565499305725
      ],
      "SF_tp2": [
        1.9999910593032837,
        2.0,
        2.0
      ],
      "SF_tp3": [
        0.756324291229248,
        0.7771321535110474,
        0.8131386041641235
      ],
      "fit": [
        0.5341792106628418,
        1.3375084400177002,
        2.0835704803466797
      ],
      "groups": [],
      "impact_SF_tp1": 0.06693041324615479,
      "impact_SF_tp2": 8.940696716308594e-06,
      "impact_SF_tp3": 0.03600645065307617,
      "name": "qcd_xsec",
      "prefit": [
        -0.9999999999999999,
        0.0,
        0.9999999999999999
      ],
      "type": "Gaussian"
    },
    {
      "SF_tp1": [
        1.1268855333328247,
        1.1394439935684204,
        1.1869219541549683
      ],
      "SF_tp2": [
        2.0,
        2.0,
        2.0
      ],
      "SF_tp3": [
        0.7831937074661255,
        0.7771103382110596,
        0.7679804563522339
      ],
      "fit": [
        -0.6561696529388428,
        0.41445988416671753,
        1.2461752891540527
      ],
      "groups": [],
      "impact_SF_tp1": 0.04747796058654785,
      "impact_SF_tp2": 0.0,
      "impact_SF_tp3": 0.009129881858825684,
      "name": "tp1JMR",
      "prefit": [
        -0.9999999999999999,
        0.0,
        0.9999999999999999
      ],
      "type": "Gaussian"
    },
    {
      "SF_tp1": [
        1.1235398054122925,
        1.139458417892456,
        1.1412421464920044
      ],
      "SF_tp2": [
        2.0,
        2.0,
        2.0
      ],
      "SF_tp3": [
        0.766680896282196,
        0.7771129608154297,
        0.7888756990432739
      ],
      "fit": [
        -1.0398839712142944,
        -0.21000327169895172,
        0.5585651993751526
      ],
      "groups": [],
      "impact_SF_tp1": 0.015918612480163574,
      "impact_SF_tp2": 0.0,
      "impact_SF_tp3": 0.011762738227844238,
      "name": "tp1JMS",
      "prefit": [
        -0.9999999999999999,
        0.0,
        0.9999999999999999
      ],
      "type": "Gaussian"
    },
    {
      "SF_tp1": [
        1.1431738138198853,
        1.139458417892456,
        1.1403123140335083
      ],
      "SF_tp2": [
        2.0,
        2.0,
        2.0
      ],
      "SF_tp3": [
        0.7714416980743408,
        0.7771129608154297,
        0.7839758396148682
      ],
      "fit": [
        -1.3106205463409424,
        -0.3572857081890106,
        0.5945488810539246
      ],
      "groups": [],
      "impact_SF_tp1": 0.0037153959274291992,
      "impact_SF_tp2": 0.0,
      "impact_SF_tp3": 0.0068628787994384766,
      "name": "tp1_xsec",
      "prefit": [
        -0.9999999999999999,
        0.0,
        0.9999999999999999
      ],
      "type": "Gaussian"
    },
    {
      "SF_tp1": [
        1.1252570152282715,
        1.1394422054290771,
        1.1753242015838623
      ],
      "SF_tp2": [
        2.0,
        2.0,
        2.0
      ],
      "SF_tp3": [
        0.791287899017334,
        0.7771115899085999,
        0.7723531126976013
      ],
      "fit": [
        -0.7644306421279907,
        -0.07496586441993713,
        0.5764845609664917
      ],
      "groups": [],
      "impact_SF_tp1": 0.035881996154785156,
      "impact_SF_tp2": 0.0,
      "impact_SF_tp3": 0.01417630910873413,
      "name": "tp2JMR",
      "prefit": [
        -0.9999999999999999,
        0.0,
        0.9999999999999999
      ],
      "type": "Gaussian"
    },
    {
      "SF_tp1": [
        1.1108249425888062,
        1.1394437551498413,
        1.1765135526657104
      ],
      "SF_tp2": [
        2.0,
        2.0,
        2.0
      ],
      "SF_tp3": [
        0.7863314747810364,
        0.7771114110946655,
        0.7717596292495728
      ],
      "fit": [
        -1.1432523727416992,
        -0.216907799243927,
        0.7259472608566284
      ],
      "groups": [],
      "impact_SF_tp1": 0.03706979751586914,
      "impact_SF_tp2": 0.0,
      "impact_SF_tp3": 0.00922006368637085,
      "name": "tp2JMS",
      "prefit": [
        -0.9999999999999999,
        0.0,
        0.9999999999999999
      ],
      "type": "Gaussian"
    },
    {
      "SF_tp1": [
        1.1854376792907715,
        1.1394575834274292,
        1.09373140335083
      ],
      "SF_tp2": [
        2.0,
        2.0,
        2.0
      ],
      "SF_tp3": [
        0.7820068597793579,
        0.7771128416061401,
        0.772297203540802
      ],
      "fit": [
        -0.931628406047821,
        0.05462857708334923,
        1.040269374847412
      ],
      "groups": [],
      "impact_SF_tp1": 0.045980095863342285,
      "impact_SF_tp2": 0.0,
      "impact_SF_tp3": 0.0048940181732177734,
      "name": "tp2_xsec",
      "prefit": [
        -0.9999999999999999,
        0.0,
        0.9999999999999999
      ],
      "type": "Gaussian"
    },
    {
      "SF_tp1": [
        1.2024341821670532,
        1.1394492387771606,
        1.0938694477081299
      ],
      "SF_tp2": [
        2.0,
        2.0,
        2.0
      ],
      "SF_tp3": [
        0.7800003886222839,
        0.7771119475364685,
        0.7861457467079163
      ],
      "fit": [
        -1.232487440109253,
        -0.6164548993110657,
        0.07419829815626144
      ],
      "groups": [],
      "impact_SF_tp1": 0.06298494338989258,
      "impact_SF_tp2": 0.0,
      "impact_SF_tp3": 0.009033799171447754,
      "name": "tp3JMR",
      "prefit": [
        -0.9999999999999999,
        0.0,
        0.9999999999999999
      ],
      "type": "Gaussian"
    },
    {
      "SF_tp1": [
        1.1292009353637695,
        1.1394572257995605,
        1.1104713678359985
      ],
      "SF_tp2": [
        2.0,
        2.0,
        2.0
      ],
      "SF_tp3": [
        0.8047729134559631,
        0.7771127820014954,
        0.771736741065979
      ],
      "fit": [
        -0.9246804118156433,
        0.13812698423862457,
        0.8861321806907654
      ],
      "groups": [],
      "impact_SF_tp1": 0.02898585796356201,
      "impact_SF_tp2": 0.0,
      "impact_SF_tp3": 0.027660131454467773,
      "name": "tp3JMS",
      "prefit": [
        -0.9999999999999999,
        0.0,
        0.9999999999999999
      ],
      "type": "Gaussian"
    },
    {
      "SF_tp1": [
        1.0937838554382324,
        1.1394577026367188,
        1.191447377204895
      ],
      "SF_tp2": [
        2.0,
        2.0,
        1.999998927116394
      ],
      "SF_tp3": [
        0.7788910269737244,
        0.7771128416061401,
        0.7770311236381531
      ],
      "fit": [
        -0.6359063982963562,
        0.30265429615974426,
        1.2443355321884155
      ],
      "groups": [],
      "impact_SF_tp1": 0.05198967456817627,
      "impact_SF_tp2": 1.0728836059570312e-06,
      "impact_SF_tp3": 0.0017781853675842285,
      "name": "tp3_xsec",
      "prefit": [
        -0.9999999999999999,
        0.0,
        0.9999999999999999
      ],
      "type": "Gaussian"
    }
  ]
}